foolish_ambitions/__init__.py
foolish_ambitions/adjacency.py
foolish_ambitions/simulator.py
foolish_ambitions/vwap.py
foolish_ambitions-0.2.0.dist-info/METADATA
foolish_ambitions-0.2.0.dist-info/WHEEL
foolish_ambitions-0.2.0.dist-info/top_level.txt
foolish_ambitions-0.2.0.dist-info/RECORD
