Metadata-Version: 2.4
Name: foolish-ambitions
Version: 0.2.0
Summary: A collection of useful functions
Author-email: Roman Chernenko <romanpeers@gmail.com>
License: MIT
Project-URL: Homepage, https://github.com/yourusername/my-package
Project-URL: Repository, https://github.com/yourusername/my-package
Project-URL: Issues, https://github.com/yourusername/my-package/issues
Keywords: utilities,functions,helpers
Classifier: Development Status :: 3 - Alpha
Classifier: Intended Audience :: Developers
Classifier: License :: OSI Approved :: MIT License
Classifier: Programming Language :: Python :: 3
Classifier: Programming Language :: Python :: 3.7
Classifier: Programming Language :: Python :: 3.8
Classifier: Programming Language :: Python :: 3.9
Classifier: Programming Language :: Python :: 3.10
Classifier: Programming Language :: Python :: 3.11
